steam_acolyte/__init__.py
steam_acolyte/__main__.py
steam_acolyte/acolyte.svg
steam_acolyte/app.py
steam_acolyte/async_.py
steam_acolyte/delete.svg
steam_acolyte/funcwrap.py
steam_acolyte/plus.svg
steam_acolyte/steam.py
steam_acolyte/steam_linux.py
steam_acolyte/steam_win32.py
steam_acolyte/theme.py
steam_acolyte/user.svg
steam_acolyte/util.py
steam_acolyte/window.css
steam_acolyte/window.py
steam_acolyte-0.10.0.dist-info/METADATA
steam_acolyte-0.10.0.dist-info/UNLICENSE
steam_acolyte-0.10.0.dist-info/WHEEL
steam_acolyte-0.10.0.dist-info/entry_points.txt
steam_acolyte-0.10.0.dist-info/top_level.txt
steam_acolyte-0.10.0.dist-info/zip-safe
steam_acolyte-0.10.0.dist-info/RECORD
