Metadata-Version: 2.1
Name: steam-acolyte
Version: 0.10.0
Summary: Lightweight user account switcher/login keeper for steam
Home-page: https://github.com/coldfix/steam-acolyte
Author: Thomas Gläßle
Author-email: thomas@coldfix.de
License: Unlicense
Platform: UNKNOWN
Classifier: Development Status :: 3 - Alpha
Classifier: Environment :: Console
Classifier: Environment :: X11 Applications :: Qt
Classifier: Intended Audience :: End Users/Desktop
Classifier: Operating System :: POSIX :: Linux
Classifier: Operating System :: Microsoft :: Windows
Classifier: Programming Language :: Python :: 3
Classifier: License :: Public Domain
Classifier: Topic :: Games/Entertainment
Requires-Python: >=3.5
Requires-Dist: pyqt5
Requires-Dist: vdf
Requires-Dist: docopt
Requires-Dist: importlib-resources ; python_version < "3.7"
